cozipy/__init__.py
cozipy/neighbors.py
cozipy/nep_cozi.py
cozipy-0.1.0.dist-info/licenses/LICENSE
cozipy-0.1.0.dist-info/METADATA
cozipy-0.1.0.dist-info/WHEEL
cozipy-0.1.0.dist-info/top_level.txt
cozipy-0.1.0.dist-info/RECORD
