Metadata-Version: 2.4
Name: cozipy
Version: 0.1.0
Summary: COZI neighbor preference analysis package
Author-email: Chiara Schiller <chiara.schiller@uni-heidelberg.de>
License: MIT License
Project-URL: Homepage, https://github.com/schapirolabor/cozipy
Project-URL: Issues, https://github.com/schapirolabor/cozipy/issues
Keywords: neighborhood,spatial,directionality
Classifier: Intended Audience :: Science/Research
Classifier: Programming Language :: Python :: 3
Classifier: License :: OSI Approved :: MIT License
Requires-Python: >=3.9
License-File: LICENSE
Requires-Dist: numpy
Requires-Dist: scipy
Requires-Dist: pandas
Dynamic: license-file
